{
  "experiment_id": "20260220_214135",
  "timestamp": "2026-02-20T21:41:35.079347",
  "ffn_mode": "VFE_dynamic",
  "config": {
    "vocab_size": 50257,
    "embed_dim": 70,
    "n_layers": 1,
    "hidden_dim": 508,
    "max_seq_len": 64,
    "learnable_alpha": false,
    "batch_size": 16,
    "use_amp": false,
    "num_workers": 6,
    "epochs": null,
    "max_steps": 100000,
    "warmup_steps": 100,
    "ffn_mode": "VFE_dynamic",
    "mask_self_attention": true,
    "tie_embeddings": false,
    "evolve_sigma": true,
    "evolve_phi": true,
    "evolve_phi_e_step": true,
    "diagonal_covariance": false,
    "use_positional_embedding": false,
    "pos_encoding_mode": "none",
    "use_identity_transport": false,
    "alibi_slope": null,
    "kappa_beta": 1.0,
    "mu_init_std": 1.0,
    "mu_normalize": false,
    "mu_max_norm": null,
    "phi_scale": 1.0,
    "ffn_n_iterations": 1,
    "ffn_learnable_lr": true,
    "ffn_chunk_size": 64,
    "mu_lr": 0.05,
    "sigma_lr": 0.005,
    "phi_lr": 0.005,
    "ffn_lr": 0.05,
    "alpha": 1,
    "beta": 1,
    "lambda_gamma": 0,
    "kappa_gamma": 1.0,
    "weight_decay": 0.01,
    "dropout": 0.1,
    "grad_clip": 1.0,
    "use_layernorm": true,
    "use_residual": false,
    "use_dropout": false,
    "log_interval": 100,
    "eval_interval": 1000,
    "checkpoint_interval": 10000,
    "semantic_analysis_interval": 5000,
    "patience": 5,
    "gauge_group": "GLK",
    "gauge_dim": 10,
    "gauge_mode": "learned",
    "use_multi_irrep": true,
    "enforce_orthogonal": false,
    "use_p_flow": false,
    "p_flow_ema_decay": 0.95,
    "use_delta_rule_w_out": false,
    "delta_rule_lr": 0.1,
    "irrep_spec": [
      [
        "fund",
        7,
        10
      ]
    ],
    "per_head_kappa": false,
    "use_output_projection": true,
    "multihead_vfe": false,
    "pos_encoding_scale": 0.3,
    "use_prior_bank": true,
    "dataset": "wikitext-103"
  },
  "args": {
    "mode": "VFE_dynamic",
    "ffn_mode": null,
    "pure_fep": false,
    "enable_sigma_phi": true,
    "prior_lr": 0.1,
    "embed_lr": 0.1,
    "device": "auto",
    "checkpoint_dir": "checkpoints_publication",
    "use_wandb": false,
    "seed": null,
    "dataset": "wikitext-103",
    "semantic_analysis_interval": 10000
  },
  "git": {
    "commit": "unknown",
    "branch": "unknown",
    "dirty": false
  },
  "system": {
    "platform": "Windows-10-10.0.19045-SP0",
    "python_version": "3.12.7",
    "torch_version": "2.10.0.dev20251210+cu128",
    "cuda_available": true,
    "cuda_version": "12.8",
    "gpu_name": "NVIDIA GeForce RTX 5090",
    "gpu_count": 1,
    "gpu_memory_gb": 34.19045888
  }
}